{
  "generated_at": "2017-02-01 08:11:12 UTC",
  "criteria": "language:Ruby stars:>20 pushed:2017-01-25..2017-01-31",
  "repos": [
    {
      "full_name": "Eric-Guo/weui-rails",
      "description": "An UI library for WeChat, includes widgets/modules in mobile web app.",
      "html_url": "https://github.com/Eric-Guo/weui-rails",
      "stars": 92,
      "language": "Ruby",
      "region": "China"
    },
    {
      "full_name": "AndorChen/rails-guides",
      "description": "Rails Guides 中文版",
      "html_url": "https://github.com/AndorChen/rails-guides",
      "stars": 55,
      "language": "Ruby",
      "region": "China"
    },
    {
      "full_name": "athrunsun/homebrew-linuxbinary",
      "description": "Precompiled binary formulae for the Linuxbrew package manager. http://linuxbrew.sh",
      "html_url": "https://github.com/athrunsun/homebrew-linuxbinary",
      "stars": 21,
      "language": "Ruby",
      "region": "China"
    }
  ]
}