{
  "generated_at": "2016-08-02 08:10:47 UTC",
  "criteria": "language:Ruby stars:>20 pushed:2016-07-17..2016-07-23",
  "repos": [
    {
      "full_name": "huacnlee/sails",
      "description": "Create a Thrift Server use like Rails",
      "html_url": "https://github.com/huacnlee/sails",
      "stars": 51,
      "language": "Ruby",
      "region": "China"
    },
    {
      "full_name": "lidaobing/capistrano-scm-jenkins",
      "description": "With this plugin, you can use jenkins build artifact as a repository, and deploy your build artifact with capistrano.",
      "html_url": "https://github.com/lidaobing/capistrano-scm-jenkins",
      "stars": 33,
      "language": "Ruby",
      "region": "China"
    }
  ]
}