{
  "login": "sumit-sr",
  "id": 14115921,
  "avatar_url": "https://avatars.githubusercontent.com/u/14115921?v=3",
  "gravatar_id": "",
  "url": "https://api.github.com/users/sumit-sr",
  "html_url": "https://github.com/sumit-sr",
  "followers_url": "https://api.github.com/users/sumit-sr/followers",
  "following_url": "https://api.github.com/users/sumit-sr/following{/other_user}",
  "gists_url": "https://api.github.com/users/sumit-sr/gists{/gist_id}",
  "starred_url": "https://api.github.com/users/sumit-sr/starred{/owner}{/repo}",
  "subscriptions_url": "https://api.github.com/users/sumit-sr/subscriptions",
  "organizations_url": "https://api.github.com/users/sumit-sr/orgs",
  "repos_url": "https://api.github.com/users/sumit-sr/repos",
  "events_url": "https://api.github.com/users/sumit-sr/events{/privacy}",
  "received_events_url": "https://api.github.com/users/sumit-sr/received_events",
  "type": "User",
  "site_admin": false,
  "score": 1.0
}