{
  "login": "Bullaaa",
  "id": 31407164,
  "avatar_url": "https://avatars2.githubusercontent.com/u/31407164?v=4",
  "gravatar_id": "",
  "url": "https://api.github.com/users/Bullaaa",
  "html_url": "https://github.com/Bullaaa",
  "followers_url": "https://api.github.com/users/Bullaaa/followers",
  "following_url": "https://api.github.com/users/Bullaaa/following{/other_user}",
  "gists_url": "https://api.github.com/users/Bullaaa/gists{/gist_id}",
  "starred_url": "https://api.github.com/users/Bullaaa/starred{/owner}{/repo}",
  "subscriptions_url": "https://api.github.com/users/Bullaaa/subscriptions",
  "organizations_url": "https://api.github.com/users/Bullaaa/orgs",
  "repos_url": "https://api.github.com/users/Bullaaa/repos",
  "events_url": "https://api.github.com/users/Bullaaa/events{/privacy}",
  "received_events_url": "https://api.github.com/users/Bullaaa/received_events",
  "type": "User",
  "site_admin": false,
  "score": 1.0
}