{
  "login": "LionsOfSavuti",
  "id": 596736,
  "avatar_url": "https://avatars.githubusercontent.com/u/596736?v=3",
  "gravatar_id": "",
  "url": "https://api.github.com/users/LionsOfSavuti",
  "html_url": "https://github.com/LionsOfSavuti",
  "followers_url": "https://api.github.com/users/LionsOfSavuti/followers",
  "following_url": "https://api.github.com/users/LionsOfSavuti/following{/other_user}",
  "gists_url": "https://api.github.com/users/LionsOfSavuti/gists{/gist_id}",
  "starred_url": "https://api.github.com/users/LionsOfSavuti/starred{/owner}{/repo}",
  "subscriptions_url": "https://api.github.com/users/LionsOfSavuti/subscriptions",
  "organizations_url": "https://api.github.com/users/LionsOfSavuti/orgs",
  "repos_url": "https://api.github.com/users/LionsOfSavuti/repos",
  "events_url": "https://api.github.com/users/LionsOfSavuti/events{/privacy}",
  "received_events_url": "https://api.github.com/users/LionsOfSavuti/received_events",
  "type": "User",
  "site_admin": false,
  "score": 1.0
}