{
  "login": "snehaso",
  "id": 907023,
  "avatar_url": "https://avatars.githubusercontent.com/u/907023?v=3",
  "gravatar_id": "",
  "url": "https://api.github.com/users/snehaso",
  "html_url": "https://github.com/snehaso",
  "followers_url": "https://api.github.com/users/snehaso/followers",
  "following_url": "https://api.github.com/users/snehaso/following{/other_user}",
  "gists_url": "https://api.github.com/users/snehaso/gists{/gist_id}",
  "starred_url": "https://api.github.com/users/snehaso/starred{/owner}{/repo}",
  "subscriptions_url": "https://api.github.com/users/snehaso/subscriptions",
  "organizations_url": "https://api.github.com/users/snehaso/orgs",
  "repos_url": "https://api.github.com/users/snehaso/repos",
  "events_url": "https://api.github.com/users/snehaso/events{/privacy}",
  "received_events_url": "https://api.github.com/users/snehaso/received_events",
  "type": "User",
  "site_admin": false,
  "score": 1.0
}