{
  "login": "haseebs",
  "id": 13743636,
  "avatar_url": "https://avatars3.githubusercontent.com/u/13743636?v=3",
  "gravatar_id": "",
  "url": "https://api.github.com/users/haseebs",
  "html_url": "https://github.com/haseebs",
  "followers_url": "https://api.github.com/users/haseebs/followers",
  "following_url": "https://api.github.com/users/haseebs/following{/other_user}",
  "gists_url": "https://api.github.com/users/haseebs/gists{/gist_id}",
  "starred_url": "https://api.github.com/users/haseebs/starred{/owner}{/repo}",
  "subscriptions_url": "https://api.github.com/users/haseebs/subscriptions",
  "organizations_url": "https://api.github.com/users/haseebs/orgs",
  "repos_url": "https://api.github.com/users/haseebs/repos",
  "events_url": "https://api.github.com/users/haseebs/events{/privacy}",
  "received_events_url": "https://api.github.com/users/haseebs/received_events",
  "type": "User",
  "site_admin": false,
  "score": 1.0
}