{
  "login": "Sohair63",
  "id": 8349026,
  "avatar_url": "https://avatars1.githubusercontent.com/u/8349026?v=4",
  "gravatar_id": "",
  "url": "https://api.github.com/users/Sohair63",
  "html_url": "https://github.com/Sohair63",
  "followers_url": "https://api.github.com/users/Sohair63/followers",
  "following_url": "https://api.github.com/users/Sohair63/following{/other_user}",
  "gists_url": "https://api.github.com/users/Sohair63/gists{/gist_id}",
  "starred_url": "https://api.github.com/users/Sohair63/starred{/owner}{/repo}",
  "subscriptions_url": "https://api.github.com/users/Sohair63/subscriptions",
  "organizations_url": "https://api.github.com/users/Sohair63/orgs",
  "repos_url": "https://api.github.com/users/Sohair63/repos",
  "events_url": "https://api.github.com/users/Sohair63/events{/privacy}",
  "received_events_url": "https://api.github.com/users/Sohair63/received_events",
  "type": "User",
  "site_admin": false,
  "score": 1.0
}