{
  "login": "llj098",
  "id": 139195,
  "avatar_url": "https://avatars.githubusercontent.com/u/139195?v=3",
  "gravatar_id": "",
  "url": "https://api.github.com/users/llj098",
  "html_url": "https://github.com/llj098",
  "followers_url": "https://api.github.com/users/llj098/followers",
  "following_url": "https://api.github.com/users/llj098/following{/other_user}",
  "gists_url": "https://api.github.com/users/llj098/gists{/gist_id}",
  "starred_url": "https://api.github.com/users/llj098/starred{/owner}{/repo}",
  "subscriptions_url": "https://api.github.com/users/llj098/subscriptions",
  "organizations_url": "https://api.github.com/users/llj098/orgs",
  "repos_url": "https://api.github.com/users/llj098/repos",
  "events_url": "https://api.github.com/users/llj098/events{/privacy}",
  "received_events_url": "https://api.github.com/users/llj098/received_events",
  "type": "User",
  "site_admin": false,
  "score": 1.0
}