{
  "login": "xianrou",
  "id": 18362639,
  "avatar_url": "https://avatars.githubusercontent.com/u/18362639?v=3",
  "gravatar_id": "",
  "url": "https://api.github.com/users/xianrou",
  "html_url": "https://github.com/xianrou",
  "followers_url": "https://api.github.com/users/xianrou/followers",
  "following_url": "https://api.github.com/users/xianrou/following{/other_user}",
  "gists_url": "https://api.github.com/users/xianrou/gists{/gist_id}",
  "starred_url": "https://api.github.com/users/xianrou/starred{/owner}{/repo}",
  "subscriptions_url": "https://api.github.com/users/xianrou/subscriptions",
  "organizations_url": "https://api.github.com/users/xianrou/orgs",
  "repos_url": "https://api.github.com/users/xianrou/repos",
  "events_url": "https://api.github.com/users/xianrou/events{/privacy}",
  "received_events_url": "https://api.github.com/users/xianrou/received_events",
  "type": "Organization",
  "site_admin": false,
  "score": 1.0
}