{
  "login": "luoleiself",
  "id": 20128158,
  "avatar_url": "https://avatars0.githubusercontent.com/u/20128158?v=4",
  "gravatar_id": "",
  "url": "https://api.github.com/users/luoleiself",
  "html_url": "https://github.com/luoleiself",
  "followers_url": "https://api.github.com/users/luoleiself/followers",
  "following_url": "https://api.github.com/users/luoleiself/following{/other_user}",
  "gists_url": "https://api.github.com/users/luoleiself/gists{/gist_id}",
  "starred_url": "https://api.github.com/users/luoleiself/starred{/owner}{/repo}",
  "subscriptions_url": "https://api.github.com/users/luoleiself/subscriptions",
  "organizations_url": "https://api.github.com/users/luoleiself/orgs",
  "repos_url": "https://api.github.com/users/luoleiself/repos",
  "events_url": "https://api.github.com/users/luoleiself/events{/privacy}",
  "received_events_url": "https://api.github.com/users/luoleiself/received_events",
  "type": "User",
  "site_admin": false,
  "score": 1.0
}