{
  "login": "mdongsheng",
  "id": 2139673,
  "avatar_url": "https://avatars.githubusercontent.com/u/2139673?v=3",
  "gravatar_id": "",
  "url": "https://api.github.com/users/mdongsheng",
  "html_url": "https://github.com/mdongsheng",
  "followers_url": "https://api.github.com/users/mdongsheng/followers",
  "following_url": "https://api.github.com/users/mdongsheng/following{/other_user}",
  "gists_url": "https://api.github.com/users/mdongsheng/gists{/gist_id}",
  "starred_url": "https://api.github.com/users/mdongsheng/starred{/owner}{/repo}",
  "subscriptions_url": "https://api.github.com/users/mdongsheng/subscriptions",
  "organizations_url": "https://api.github.com/users/mdongsheng/orgs",
  "repos_url": "https://api.github.com/users/mdongsheng/repos",
  "events_url": "https://api.github.com/users/mdongsheng/events{/privacy}",
  "received_events_url": "https://api.github.com/users/mdongsheng/received_events",
  "type": "User",
  "site_admin": false,
  "score": 1.0
}