{
  "login": "whengyu",
  "id": 2193463,
  "avatar_url": "https://avatars.githubusercontent.com/u/2193463?v=3",
  "gravatar_id": "",
  "url": "https://api.github.com/users/whengyu",
  "html_url": "https://github.com/whengyu",
  "followers_url": "https://api.github.com/users/whengyu/followers",
  "following_url": "https://api.github.com/users/whengyu/following{/other_user}",
  "gists_url": "https://api.github.com/users/whengyu/gists{/gist_id}",
  "starred_url": "https://api.github.com/users/whengyu/starred{/owner}{/repo}",
  "subscriptions_url": "https://api.github.com/users/whengyu/subscriptions",
  "organizations_url": "https://api.github.com/users/whengyu/orgs",
  "repos_url": "https://api.github.com/users/whengyu/repos",
  "events_url": "https://api.github.com/users/whengyu/events{/privacy}",
  "received_events_url": "https://api.github.com/users/whengyu/received_events",
  "type": "User",
  "site_admin": false,
  "score": 1.0
}