{
  "login": "Hxiaongrong",
  "id": 21995182,
  "avatar_url": "https://avatars3.githubusercontent.com/u/21995182?v=4",
  "gravatar_id": "",
  "url": "https://api.github.com/users/Hxiaongrong",
  "html_url": "https://github.com/Hxiaongrong",
  "followers_url": "https://api.github.com/users/Hxiaongrong/followers",
  "following_url": "https://api.github.com/users/Hxiaongrong/following{/other_user}",
  "gists_url": "https://api.github.com/users/Hxiaongrong/gists{/gist_id}",
  "starred_url": "https://api.github.com/users/Hxiaongrong/starred{/owner}{/repo}",
  "subscriptions_url": "https://api.github.com/users/Hxiaongrong/subscriptions",
  "organizations_url": "https://api.github.com/users/Hxiaongrong/orgs",
  "repos_url": "https://api.github.com/users/Hxiaongrong/repos",
  "events_url": "https://api.github.com/users/Hxiaongrong/events{/privacy}",
  "received_events_url": "https://api.github.com/users/Hxiaongrong/received_events",
  "type": "User",
  "site_admin": false,
  "score": 1.0
}