{
  "login": "zuohaisu",
  "id": 2510853,
  "avatar_url": "https://avatars.githubusercontent.com/u/2510853?v=3",
  "gravatar_id": "",
  "url": "https://api.github.com/users/zuohaisu",
  "html_url": "https://github.com/zuohaisu",
  "followers_url": "https://api.github.com/users/zuohaisu/followers",
  "following_url": "https://api.github.com/users/zuohaisu/following{/other_user}",
  "gists_url": "https://api.github.com/users/zuohaisu/gists{/gist_id}",
  "starred_url": "https://api.github.com/users/zuohaisu/starred{/owner}{/repo}",
  "subscriptions_url": "https://api.github.com/users/zuohaisu/subscriptions",
  "organizations_url": "https://api.github.com/users/zuohaisu/orgs",
  "repos_url": "https://api.github.com/users/zuohaisu/repos",
  "events_url": "https://api.github.com/users/zuohaisu/events{/privacy}",
  "received_events_url": "https://api.github.com/users/zuohaisu/received_events",
  "type": "User",
  "site_admin": false,
  "score": 1.0
}