{
  "login": "xnjiang",
  "id": 315021,
  "avatar_url": "https://avatars.githubusercontent.com/u/315021?v=3",
  "gravatar_id": "",
  "url": "https://api.github.com/users/xnjiang",
  "html_url": "https://github.com/xnjiang",
  "followers_url": "https://api.github.com/users/xnjiang/followers",
  "following_url": "https://api.github.com/users/xnjiang/following{/other_user}",
  "gists_url": "https://api.github.com/users/xnjiang/gists{/gist_id}",
  "starred_url": "https://api.github.com/users/xnjiang/starred{/owner}{/repo}",
  "subscriptions_url": "https://api.github.com/users/xnjiang/subscriptions",
  "organizations_url": "https://api.github.com/users/xnjiang/orgs",
  "repos_url": "https://api.github.com/users/xnjiang/repos",
  "events_url": "https://api.github.com/users/xnjiang/events{/privacy}",
  "received_events_url": "https://api.github.com/users/xnjiang/received_events",
  "type": "User",
  "site_admin": false,
  "score": 1.0
}