{
  "login": "hui",
  "id": 5476,
  "avatar_url": "https://avatars.githubusercontent.com/u/5476?v=3",
  "gravatar_id": "",
  "url": "https://api.github.com/users/hui",
  "html_url": "https://github.com/hui",
  "followers_url": "https://api.github.com/users/hui/followers",
  "following_url": "https://api.github.com/users/hui/following{/other_user}",
  "gists_url": "https://api.github.com/users/hui/gists{/gist_id}",
  "starred_url": "https://api.github.com/users/hui/starred{/owner}{/repo}",
  "subscriptions_url": "https://api.github.com/users/hui/subscriptions",
  "organizations_url": "https://api.github.com/users/hui/orgs",
  "repos_url": "https://api.github.com/users/hui/repos",
  "events_url": "https://api.github.com/users/hui/events{/privacy}",
  "received_events_url": "https://api.github.com/users/hui/received_events",
  "type": "User",
  "site_admin": false,
  "score": 1.0
}