{
  "login": "getqujing",
  "id": 8080366,
  "avatar_url": "https://avatars.githubusercontent.com/u/8080366?v=3",
  "gravatar_id": "",
  "url": "https://api.github.com/users/getqujing",
  "html_url": "https://github.com/getqujing",
  "followers_url": "https://api.github.com/users/getqujing/followers",
  "following_url": "https://api.github.com/users/getqujing/following{/other_user}",
  "gists_url": "https://api.github.com/users/getqujing/gists{/gist_id}",
  "starred_url": "https://api.github.com/users/getqujing/starred{/owner}{/repo}",
  "subscriptions_url": "https://api.github.com/users/getqujing/subscriptions",
  "organizations_url": "https://api.github.com/users/getqujing/orgs",
  "repos_url": "https://api.github.com/users/getqujing/repos",
  "events_url": "https://api.github.com/users/getqujing/events{/privacy}",
  "received_events_url": "https://api.github.com/users/getqujing/received_events",
  "type": "Organization",
  "site_admin": false,
  "score": 1.0
}