{
  "login": "farcrew-94",
  "id": 18186366,
  "avatar_url": "https://avatars3.githubusercontent.com/u/18186366?v=4",
  "gravatar_id": "",
  "url": "https://api.github.com/users/farcrew-94",
  "html_url": "https://github.com/farcrew-94",
  "followers_url": "https://api.github.com/users/farcrew-94/followers",
  "following_url": "https://api.github.com/users/farcrew-94/following{/other_user}",
  "gists_url": "https://api.github.com/users/farcrew-94/gists{/gist_id}",
  "starred_url": "https://api.github.com/users/farcrew-94/starred{/owner}{/repo}",
  "subscriptions_url": "https://api.github.com/users/farcrew-94/subscriptions",
  "organizations_url": "https://api.github.com/users/farcrew-94/orgs",
  "repos_url": "https://api.github.com/users/farcrew-94/repos",
  "events_url": "https://api.github.com/users/farcrew-94/events{/privacy}",
  "received_events_url": "https://api.github.com/users/farcrew-94/received_events",
  "type": "User",
  "site_admin": false,
  "score": 1.0
}