{
  "login": "hico-horiuchi",
  "id": 1259714,
  "avatar_url": "https://avatars1.githubusercontent.com/u/1259714?v=4",
  "gravatar_id": "",
  "url": "https://api.github.com/users/hico-horiuchi",
  "html_url": "https://github.com/hico-horiuchi",
  "followers_url": "https://api.github.com/users/hico-horiuchi/followers",
  "following_url": "https://api.github.com/users/hico-horiuchi/following{/other_user}",
  "gists_url": "https://api.github.com/users/hico-horiuchi/gists{/gist_id}",
  "starred_url": "https://api.github.com/users/hico-horiuchi/starred{/owner}{/repo}",
  "subscriptions_url": "https://api.github.com/users/hico-horiuchi/subscriptions",
  "organizations_url": "https://api.github.com/users/hico-horiuchi/orgs",
  "repos_url": "https://api.github.com/users/hico-horiuchi/repos",
  "events_url": "https://api.github.com/users/hico-horiuchi/events{/privacy}",
  "received_events_url": "https://api.github.com/users/hico-horiuchi/received_events",
  "type": "User",
  "site_admin": false,
  "score": 1.0
}