{
  "login": "krlab-kut",
  "id": 16247274,
  "avatar_url": "https://avatars.githubusercontent.com/u/16247274?v=3",
  "gravatar_id": "",
  "url": "https://api.github.com/users/krlab-kut",
  "html_url": "https://github.com/krlab-kut",
  "followers_url": "https://api.github.com/users/krlab-kut/followers",
  "following_url": "https://api.github.com/users/krlab-kut/following{/other_user}",
  "gists_url": "https://api.github.com/users/krlab-kut/gists{/gist_id}",
  "starred_url": "https://api.github.com/users/krlab-kut/starred{/owner}{/repo}",
  "subscriptions_url": "https://api.github.com/users/krlab-kut/subscriptions",
  "organizations_url": "https://api.github.com/users/krlab-kut/orgs",
  "repos_url": "https://api.github.com/users/krlab-kut/repos",
  "events_url": "https://api.github.com/users/krlab-kut/events{/privacy}",
  "received_events_url": "https://api.github.com/users/krlab-kut/received_events",
  "type": "Organization",
  "site_admin": false,
  "score": 1.0
}