{
  "login": "mhiro2",
  "id": 24864588,
  "avatar_url": "https://avatars2.githubusercontent.com/u/24864588?v=4",
  "gravatar_id": "",
  "url": "https://api.github.com/users/mhiro2",
  "html_url": "https://github.com/mhiro2",
  "followers_url": "https://api.github.com/users/mhiro2/followers",
  "following_url": "https://api.github.com/users/mhiro2/following{/other_user}",
  "gists_url": "https://api.github.com/users/mhiro2/gists{/gist_id}",
  "starred_url": "https://api.github.com/users/mhiro2/starred{/owner}{/repo}",
  "subscriptions_url": "https://api.github.com/users/mhiro2/subscriptions",
  "organizations_url": "https://api.github.com/users/mhiro2/orgs",
  "repos_url": "https://api.github.com/users/mhiro2/repos",
  "events_url": "https://api.github.com/users/mhiro2/events{/privacy}",
  "received_events_url": "https://api.github.com/users/mhiro2/received_events",
  "type": "User",
  "site_admin": false,
  "score": 1.0
}