{
  "login": "fanliming",
  "id": 3654543,
  "avatar_url": "https://avatars.githubusercontent.com/u/3654543?v=3",
  "gravatar_id": "",
  "url": "https://api.github.com/users/fanliming",
  "html_url": "https://github.com/fanliming",
  "followers_url": "https://api.github.com/users/fanliming/followers",
  "following_url": "https://api.github.com/users/fanliming/following{/other_user}",
  "gists_url": "https://api.github.com/users/fanliming/gists{/gist_id}",
  "starred_url": "https://api.github.com/users/fanliming/starred{/owner}{/repo}",
  "subscriptions_url": "https://api.github.com/users/fanliming/subscriptions",
  "organizations_url": "https://api.github.com/users/fanliming/orgs",
  "repos_url": "https://api.github.com/users/fanliming/repos",
  "events_url": "https://api.github.com/users/fanliming/events{/privacy}",
  "received_events_url": "https://api.github.com/users/fanliming/received_events",
  "type": "User",
  "site_admin": false,
  "score": 1.0
}