{
  "login": "cu39",
  "id": 46552,
  "avatar_url": "https://avatars.githubusercontent.com/u/46552?v=3",
  "gravatar_id": "",
  "url": "https://api.github.com/users/cu39",
  "html_url": "https://github.com/cu39",
  "followers_url": "https://api.github.com/users/cu39/followers",
  "following_url": "https://api.github.com/users/cu39/following{/other_user}",
  "gists_url": "https://api.github.com/users/cu39/gists{/gist_id}",
  "starred_url": "https://api.github.com/users/cu39/starred{/owner}{/repo}",
  "subscriptions_url": "https://api.github.com/users/cu39/subscriptions",
  "organizations_url": "https://api.github.com/users/cu39/orgs",
  "repos_url": "https://api.github.com/users/cu39/repos",
  "events_url": "https://api.github.com/users/cu39/events{/privacy}",
  "received_events_url": "https://api.github.com/users/cu39/received_events",
  "type": "User",
  "site_admin": false,
  "score": 1.0
}