{
  "login": "YoshimichiOno",
  "id": 9762272,
  "avatar_url": "https://avatars.githubusercontent.com/u/9762272?v=3",
  "gravatar_id": "",
  "url": "https://api.github.com/users/YoshimichiOno",
  "html_url": "https://github.com/YoshimichiOno",
  "followers_url": "https://api.github.com/users/YoshimichiOno/followers",
  "following_url": "https://api.github.com/users/YoshimichiOno/following{/other_user}",
  "gists_url": "https://api.github.com/users/YoshimichiOno/gists{/gist_id}",
  "starred_url": "https://api.github.com/users/YoshimichiOno/starred{/owner}{/repo}",
  "subscriptions_url": "https://api.github.com/users/YoshimichiOno/subscriptions",
  "organizations_url": "https://api.github.com/users/YoshimichiOno/orgs",
  "repos_url": "https://api.github.com/users/YoshimichiOno/repos",
  "events_url": "https://api.github.com/users/YoshimichiOno/events{/privacy}",
  "received_events_url": "https://api.github.com/users/YoshimichiOno/received_events",
  "type": "User",
  "site_admin": false,
  "score": 1.0
}