{
  "generated_at": "2016-06-15 08:11:20 UTC",
  "criteria": "language:Ruby stars:>20 pushed:2016-06-08..2016-06-14",
  "repos": [
    {
      "full_name": "gazay/gon",
      "description": "Your Rails variables in your JS",
      "html_url": "https://github.com/gazay/gon",
      "stars": 2126,
      "language": "Ruby",
      "region": "Singapore"
    },
    {
      "full_name": "jollygoodcode/jollygoodcode.github.io",
      "description": ":thought_balloon: Jolly Good Blog",
      "html_url": "https://github.com/jollygoodcode/jollygoodcode.github.io",
      "stars": 72,
      "language": "Ruby",
      "region": "Singapore"
    },
    {
      "full_name": "jollygoodcode/twemoji",
      "description": ":shipit: Twitter emoji in Ruby :blush:",
      "html_url": "https://github.com/jollygoodcode/twemoji",
      "stars": 50,
      "language": "Ruby",
      "region": "Singapore"
    },
    {
      "full_name": "Coursemology/coursemology2",
      "description": "Rails 4 re-write of Coursemology",
      "html_url": "https://github.com/Coursemology/coursemology2",
      "stars": 24,
      "language": "Ruby",
      "region": "Singapore"
    }
  ]
}