{
  "login": "HasithaDananjaya",
  "id": 3830595,
  "avatar_url": "https://avatars0.githubusercontent.com/u/3830595?v=4",
  "gravatar_id": "",
  "url": "https://api.github.com/users/HasithaDananjaya",
  "html_url": "https://github.com/HasithaDananjaya",
  "followers_url": "https://api.github.com/users/HasithaDananjaya/followers",
  "following_url": "https://api.github.com/users/HasithaDananjaya/following{/other_user}",
  "gists_url": "https://api.github.com/users/HasithaDananjaya/gists{/gist_id}",
  "starred_url": "https://api.github.com/users/HasithaDananjaya/starred{/owner}{/repo}",
  "subscriptions_url": "https://api.github.com/users/HasithaDananjaya/subscriptions",
  "organizations_url": "https://api.github.com/users/HasithaDananjaya/orgs",
  "repos_url": "https://api.github.com/users/HasithaDananjaya/repos",
  "events_url": "https://api.github.com/users/HasithaDananjaya/events{/privacy}",
  "received_events_url": "https://api.github.com/users/HasithaDananjaya/received_events",
  "type": "User",
  "site_admin": false,
  "score": 1.0
}