{
  "login": "canburak",
  "id": 226693,
  "avatar_url": "https://avatars.githubusercontent.com/u/226693?v=3",
  "gravatar_id": "",
  "url": "https://api.github.com/users/canburak",
  "html_url": "https://github.com/canburak",
  "followers_url": "https://api.github.com/users/canburak/followers",
  "following_url": "https://api.github.com/users/canburak/following{/other_user}",
  "gists_url": "https://api.github.com/users/canburak/gists{/gist_id}",
  "starred_url": "https://api.github.com/users/canburak/starred{/owner}{/repo}",
  "subscriptions_url": "https://api.github.com/users/canburak/subscriptions",
  "organizations_url": "https://api.github.com/users/canburak/orgs",
  "repos_url": "https://api.github.com/users/canburak/repos",
  "events_url": "https://api.github.com/users/canburak/events{/privacy}",
  "received_events_url": "https://api.github.com/users/canburak/received_events",
  "type": "User",
  "site_admin": false,
  "score": 1.0
}